yangsuite_restconf-2.1.12.dist-info/licenses/LICENSE.txt
ysrestconf/__init__.py
ysrestconf/_version.py
ysrestconf/ansible.py
ysrestconf/ansible_helper.py
ysrestconf/apps.py
ysrestconf/device_plugin.py
ysrestconf/restconf.py
ysrestconf/rmodels.py
ysrestconf/urls.py
ysrestconf/views.py
ysrestconf/static/ysrestconf/bundle/ysrestconf-ui-28a5b5b703ea51dc755e.js
ysrestconf/static/ysrestconf/bundle/ysrestconf-ui-28a5b5b703ea51dc755e.js.LICENSE.txt
ysrestconf/static/ysrestconf/css/demo.css
ysrestconf/static/ysrestconf/css/navbar.css
ysrestconf/static/ysrestconf/css/offcanvas.css
ysrestconf/static/ysrestconf/css/yagger.css
ysrestconf/static/ysrestconf/docs/.buildinfo
ysrestconf/static/ysrestconf/docs/environment.pickle
ysrestconf/static/ysrestconf/docs/genindex.fjson
ysrestconf/static/ysrestconf/docs/genindex.html
ysrestconf/static/ysrestconf/docs/globalcontext.json
ysrestconf/static/ysrestconf/docs/index.fjson
ysrestconf/static/ysrestconf/docs/index.html
ysrestconf/static/ysrestconf/docs/last_build
ysrestconf/static/ysrestconf/docs/objects.inv
ysrestconf/static/ysrestconf/docs/restconf.fjson
ysrestconf/static/ysrestconf/docs/restconf.html
ysrestconf/static/ysrestconf/docs/search.fjson
ysrestconf/static/ysrestconf/docs/search.html
ysrestconf/static/ysrestconf/docs/searchindex.js
ysrestconf/static/ysrestconf/docs/searchindex.json
ysrestconf/static/ysrestconf/docs/.doctrees/environment.pickle
ysrestconf/static/ysrestconf/docs/.doctrees/index.doctree
ysrestconf/static/ysrestconf/docs/.doctrees/restconf.doctree
ysrestconf/static/ysrestconf/docs/_sources/index.rst.txt
ysrestconf/static/ysrestconf/docs/_sources/restconf.rst.txt
ysrestconf/static/ysrestconf/docs/_static/basic.css
ysrestconf/static/ysrestconf/docs/_static/doctools.js
ysrestconf/static/ysrestconf/docs/_static/documentation_options.js
ysrestconf/static/ysrestconf/docs/_static/file.png
ysrestconf/static/ysrestconf/docs/_static/language_data.js
ysrestconf/static/ysrestconf/docs/_static/minus.png
ysrestconf/static/ysrestconf/docs/_static/plus.png
yangsuite_restconf-2.1.12.dist-info/METADATA
yangsuite_restconf-2.1.12.dist-info/WHEEL
yangsuite_restconf-2.1.12.dist-info/entry_points.txt
yangsuite_restconf-2.1.12.dist-info/top_level.txt
yangsuite_restconf-2.1.12.dist-info/RECORD
