Metadata-Version: 2.4
Name: yangsuite-restconf
Version: 2.1.12
Summary: RESTCONF protocol
Home-page: https://developer.cisco.com/yangsuite
Author: YANG Suite development team
Author-email: yangsuite-support-ext@cisco.com
License: Cisco General Terms
Requires-Python: >=3.6
License-File: LICENSE.txt
Requires-Dist: yangsuite>=3.0.0
Requires-Dist: yangsuite-yangtree>=2.0.0
Requires-Dist: yangsuite-filemanager<2.0.0,>=1.4.0
Requires-Dist: yangsuite-devices<3.0.0,>=2.0.0
Requires-Dist: pyyaml
Dynamic: author
Dynamic: author-email
Dynamic: description
Dynamic: home-page
Dynamic: license
Dynamic: license-file
Dynamic: requires-dist
Dynamic: requires-python
Dynamic: summary
